rehash/__init__.py
rehash/structs.py
rehash-1.0.1.dist-info/LICENSE
rehash-1.0.1.dist-info/METADATA
rehash-1.0.1.dist-info/WHEEL
rehash-1.0.1.dist-info/top_level.txt
rehash-1.0.1.dist-info/RECORD
